COPYING
MANIFEST.in
README.rst
setup.py
drcsterm/__init__.py
drcsterm/drcsterm.py
drcsterm.egg-info/PKG-INFO
drcsterm.egg-info/SOURCES.txt
drcsterm.egg-info/dependency_links.txt
drcsterm.egg-info/eager_resources.txt
drcsterm.egg-info/entry_points.txt
drcsterm.egg-info/top_level.txt
drcsterm.egg-info/zip-safe
drcsterm/tff/__init__.py
drcsterm/tff/setup.py
drcsterm/tff/tff.py