Metadata-Version: 1.1
Name: drcsterm
Version: 0.1.2
Summary: UCS Private Area (Plain 16) -> DRCS conversion filter for terminal
Home-page: https://github.com/saitoha/drcsterm
Author: Hayaki Saito (user@zuse.jp)
Author-email: user@zuse.jp
License: GPL v3
Keywords: DRCS terminal
Platform: UNKNOWN
Classifier: Development Status :: 4 - Beta
Classifier: Topic :: Terminals
Classifier: Environment :: Console
Classifier: Intended Audience :: End Users/Desktop
Classifier: License :: OSI Approved :: GNU General Public License (GPL)
Classifier: Programming Language :: Python
